stp/__init__.py
stp/exceptions.py
stp/interfaces.py
stp/server.py
stp/settings.py
stp/stp_server/__init__.py
stp/stp_server/stp_server.py
stp/stp_server/transilation/__init__.py
stp/stp_server/transilation/transilation.py
stp/stp_server/transilation/enc/__init__.py
stp/stp_server/transilation/enc/crypt.py
stp/stp_server/transport/__init__.py
stp/stp_server/transport/interfaces.py
stp/stp_server/transport/transport.py
stp_server-0.1.2.dist-info/LICENSE
stp_server-0.1.2.dist-info/METADATA
stp_server-0.1.2.dist-info/WHEEL
stp_server-0.1.2.dist-info/top_level.txt
stp_server-0.1.2.dist-info/RECORD
